testing_framework_client/__init__.py
testing_framework_client/auth.py
testing_framework_client/client.py
testing_framework_client/printing.py
testing_framework_client-0.0.2.dist-info/METADATA
testing_framework_client-0.0.2.dist-info/WHEEL
testing_framework_client-0.0.2.dist-info/top_level.txt
testing_framework_client-0.0.2.dist-info/RECORD
