Metadata-Version: 2.4
Name: testing_framework_client
Version: 0.0.2
Summary: Python client for Testing Framework public endpoints with automatic token refresh
Author-email: Kristian Pilegaard Jensen <kristian.jensen@spirii.com>
License: MIT
Classifier: Programming Language :: Python :: 3
Classifier: Operating System :: OS Independent
Requires-Python: >=3.9
Requires-Dist: requests>=2.28
Requires-Dist: colorama>=0.4.6
Requires-Dist: python-dotenv>=1.0.0
